platformspec/__init__.py
platformspec/api/__init__.py
platformspec/api/v1alpha1/Cluster.py
platformspec/api/v1alpha1/Credential.py
platformspec/api/v1alpha1/Environment.py
platformspec/api/v1alpha1/Image.py
platformspec/api/v1alpha1/Network.py
platformspec/api/v1alpha1/Platform.py
platformspec/api/v1alpha1/Provider.py
platformspec/api/v1alpha1/Server.py
platformspec/api/v1alpha1/SoftwareGroup.py
platformspec/api/v1alpha1/__init__.py
platformspec-0.1.0.dist-info/LICENSE
platformspec-0.1.0.dist-info/METADATA
platformspec-0.1.0.dist-info/WHEEL
platformspec-0.1.0.dist-info/RECORD
